{
    "name": "Base16 Atelier Lakeside",
    "background": "#161b1d",    // base00
    "foreground": "#7ea2b4",    // base05
    "black": "#161b1d",         // base00
    "red": "#d22d72",           // base08
    "green": "#568c3b",         // base0B
    //"yellow": "#935c25",        // base09
    "yellow": "#8a8a0f",        // base0A
    "blue": "#257fad",          // base0D
    "purple": "#6b6bb8",        // base0E
    "cyan": "#2d8f6f",          // base0C
    "white": "#7ea2b4",         // base05
    "brightBlack": "#5a7b8c",   // base03
    //"brightRed": "#7195a8",     // base04
    "brightRed": "#d22d72",     // base08
    //"brightGreen": "#516d7b",   // base02
    "brightGreen": "#568c3b",   // base0B
    //"brightYellow": "#c1e4f6",  // base06
    "brightYellow": "#8a8a0f",  // base0A
    //"brightBlue": "#1f292e",    // base01
    "brightBlue": "#257fad",    // base0D
    //"brightPurple": "#7ea2b4",  // base05
    "brightPurple": "#6b6bb8",  // base0E
    //"brightCyan": "#5a7b8c",    // base03
    "brightCyan": "#2d8f6f",    // base0C
    "brightWhite": "#ebf8ff"    // base07
}
